blurredface_sts_test/__init__.py
blurredface_sts_test/face.py
blurredface_sts_test/haarcascades/haarcascade_eye.xml
blurredface_sts_test/haarcascades/haarcascade_eye_tree_eyeglasses.xml
blurredface_sts_test/haarcascades/haarcascade_frontalcatface.xml
blurredface_sts_test/haarcascades/haarcascade_frontalcatface_extended.xml
blurredface_sts_test/haarcascades/haarcascade_frontalface_alt.xml
blurredface_sts_test/haarcascades/haarcascade_frontalface_alt2.xml
blurredface_sts_test/haarcascades/haarcascade_frontalface_alt_tree.xml
blurredface_sts_test/haarcascades/haarcascade_frontalface_default.xml
blurredface_sts_test/haarcascades/haarcascade_fullbody.xml
blurredface_sts_test/haarcascades/haarcascade_lefteye_2splits.xml
blurredface_sts_test/haarcascades/haarcascade_licence_plate_rus_16stages.xml
blurredface_sts_test/haarcascades/haarcascade_lowerbody.xml
blurredface_sts_test/haarcascades/haarcascade_profileface.xml
blurredface_sts_test/haarcascades/haarcascade_righteye_2splits.xml
blurredface_sts_test/haarcascades/haarcascade_russian_plate_number.xml
blurredface_sts_test/haarcascades/haarcascade_smile.xml
blurredface_sts_test/haarcascades/haarcascade_upperbody.xml
blurredface_sts_test-0.2.1.dist-info/METADATA
blurredface_sts_test-0.2.1.dist-info/WHEEL
blurredface_sts_test-0.2.1.dist-info/top_level.txt
blurredface_sts_test-0.2.1.dist-info/RECORD
