Metadata-Version: 2.1
Name: blurredface-sts-test
Version: 0.2.1
Summary: Blurred face
Home-page: UNKNOWN
Author: Leesudong
Author-email: 905412718@qq.com
License: apache 3.0
Platform: UNKNOWN
Requires: numpy
Requires: matplotlib
